pbot
