Metadata-Version: 1.0
Name: pbot
Version: 1.4.0
Summary: An simple site crawler with proxy support
Home-page: http://bitbucket.org/zeus/pbot
Author: Pavel Zhukov
Author-email: gelios@gmail.com
License: GPL
Keywords: crawling,bot
Platform: UNKNOWN
